{
  "diagnostic.displayByAle": true,
  "diagnostic.format": "%message [%source]",
  "diagnostic.enableSign": true,
  "diagnostic.errorSign": "´ćł ",
  "diagnostic.warningSign": "´ü▒ ",
  "diagnostic.infoSign": "´âź ",
  "diagnostic.hintSign": "´éş ",
  "diagnostic.messageTarget": "float",
  "diagnostic.virtualText": true,
  "diagnostic.enableMessage": "always",
  "diagnostic.checkCurrentLine": true,
  "diagnostic.virtualTextPrefix": "  ´ĹŻ´ĹŻ ´Ĺ»  ",
  "diagnostic.separateRelatedInformationAsDiagnostics": true,
  "git.changeRemovedSign.text": "ÔÄ╣",
  "git.branchCharacter": "ţťą",
  "git.changedDecorator": "ţčë",
  "git.changedSign.text": "ţčë",
  "git.addedSign.text": "ţčë",
  "git.removedSign.text": "ţčë",
  "highlight.colors.enable": false,
  "highlight.document.enable": true,
  "pairs.enableCharacters": ["(", "[", "{", "'", "\"", "`"],
  "prettier.tabWidth": 2,
  "suggest.noselect": false,
  "suggest.disableMenu": true,
  "suggest.completionItemKindLabels": {
    "keyword": "´ç× ",
    "variable": "´žŞ ",
    "value": "´óč ",
    "operator": "´Śź ",
    "function": "´úľ ",
    "reference": "´ęć ",
    "constant": "´žŞ",
    "method": "´úľ ",
    "struct": "´şä ",
    "class": "´şä",
    "interface": "´ÉŚ ",
    "text": "ţśĺ",
    "enum": "´ÉÁ ",
    "enumMember": "´Ł║ ",
    "module": "ţśő ",
    "color": "´úŚ ",
    "property": "´éş ",
    "field": "´░á ",
    "unit": "´ąČ ",
    "event": "´âž ",
    "file": "´ťô ",
    "folder": "´ŁŐ ",
    "snippet": "´Čĺ ",
    "typeParameter": "´×â ",
    "default": "ţśĺ "
  },
  "yank.highlight.duration": 5000,
  "coc.preferences.colorSupport": true,
  "coc.preferences.extensionUpdateCheck": "never",
  "coc.preferences.formatOnSaveFiletypes": [
    "javascript",
    "typescript",
    "typescriptreact",
    "json",
    "javascriptreact",
    "typescript.tsx",
    "graphql"
  ]
}
